README.txt
setup.py
collective/__init__.py
collective.bumblebee.egg-info/PKG-INFO
collective.bumblebee.egg-info/SOURCES.txt
collective.bumblebee.egg-info/dependency_links.txt
collective.bumblebee.egg-info/entry_points.txt
collective.bumblebee.egg-info/namespace_packages.txt
collective.bumblebee.egg-info/not-zip-safe
collective.bumblebee.egg-info/requires.txt
collective.bumblebee.egg-info/top_level.txt
collective/bumblebee/__init__.py
collective/bumblebee/cache.py
collective/bumblebee/conditions.py
collective/bumblebee/configure.zcml
collective/bumblebee/interfaces.py
collective/bumblebee/rules.py
collective/bumblebee/selectors.py
collective/bumblebee/tests.py
collective/bumblebee/transform.py
collective/bumblebee/utils.py
collective/bumblebee/profiles/default/browserlayer.xml
collective/bumblebee/profiles/default/metadata.xml
collective/bumblebee/profiles/default/registry.xml
docs/HISTORY.txt
docs/INSTALL.txt
docs/LICENSE.GPL
docs/LICENSE.txt