Metadata-Version: 1.0
Name: collective.bumblebee
Version: 1.0a2
Summary: Integration of Bumblebee into plone
Home-page: https://github.com/vangheem/collective.bumblebee
Author: Nathan Van Gheem
Author-email: vangheem@gmail.com
License: GPL
Keywords: plone theming diazo deliverance bumblebee
Platform: UNKNOWN
Classifier: Framework :: Plone
Classifier: Programming Language :: Python
